mastobot/__init__.py
mastobot/__main__.py
mastobot/constants.py
mastobot/html_text.py
mastobot/structs.py
mastobot/trigger.py
mastobot/ws.py
tests/__init__.py
tests/__main__.py
tests/test_html_text.py
tests/test_ws.py
mastobot-0.2.1.dist-info/LICENSE
mastobot-0.2.1.dist-info/METADATA
mastobot-0.2.1.dist-info/WHEEL
mastobot-0.2.1.dist-info/top_level.txt
mastobot-0.2.1.dist-info/RECORD
