Metadata-Version: 2.1
Name: mastobot
Version: 0.2.1
Summary: Create cheap Mastodon bots in a Flask-like syntax
Home-page: https://git.sr.ht/~fkfd/mastobot
Author: Frederick Yin
Author-email: fkfd@macaw.me
License: 0BSD
Keywords: mastodon bot
Platform: UNKNOWN
Classifier: Development Status :: 3 - Alpha
Classifier: License :: Public Domain
Requires-Python: >=3.6
Requires-Dist: Mastodon.py
Requires-Dist: websockets
Requires-Dist: lxml
